openadapt_retrieval/__init__.py
openadapt_retrieval/cli.py
openadapt_retrieval/embeddings/__init__.py
openadapt_retrieval/embeddings/base.py
openadapt_retrieval/embeddings/clip.py
openadapt_retrieval/embeddings/qwen3vl.py
openadapt_retrieval/embeddings/registry.py
openadapt_retrieval/retriever/__init__.py
openadapt_retrieval/retriever/demo_retriever.py
openadapt_retrieval/retriever/index.py
openadapt_retrieval/retriever/reranker.py
openadapt_retrieval/storage/__init__.py
openadapt_retrieval/storage/persistence.py
openadapt_retrieval-0.1.2.dist-info/METADATA
openadapt_retrieval-0.1.2.dist-info/WHEEL
openadapt_retrieval-0.1.2.dist-info/entry_points.txt
openadapt_retrieval-0.1.2.dist-info/licenses/LICENSE
openadapt_retrieval-0.1.2.dist-info/RECORD
