Metadata-Version: 2.4
Name: openadapt-retrieval
Version: 0.1.2
Summary: Multimodal demo retrieval using VLM embeddings for GUI automation
Project-URL: Homepage, https://github.com/OpenAdaptAI/openadapt-retrieval
Project-URL: Repository, https://github.com/OpenAdaptAI/openadapt-retrieval
Project-URL: Documentation, https://github.com/OpenAdaptAI/openadapt-retrieval#readme
Project-URL: Issues, https://github.com/OpenAdaptAI/openadapt-retrieval/issues
Project-URL: Changelog, https://github.com/OpenAdaptAI/openadapt-retrieval/releases
Author-email: Richard Abrich <richard@openadapt.ai>
Maintainer-email: OpenAdaptAI <info@openadapt.ai>
License-Expression: MIT
License-File: LICENSE
Keywords: automation,embeddings,faiss,gui,multimodal,retrieval,vlm
Classifier: Development Status :: 3 - Alpha
Classifier: Intended Audience :: Developers
Classifier: License :: OSI Approved :: MIT License
Classifier: Programming Language :: Python :: 3
Classifier: Programming Language :: Python :: 3.10
Classifier: Programming Language :: Python :: 3.11
Classifier: Programming Language :: Python :: 3.12
Classifier: Topic :: Scientific/Engineering :: Artificial Intelligence
Classifier: Topic :: Software Development :: Libraries :: Python Modules
Requires-Python: >=3.10
Requires-Dist: faiss-cpu>=1.7.4
Requires-Dist: numpy>=1.24.0
Requires-Dist: pillow>=10.0.0
Requires-Dist: pydantic>=2.0.0
Requires-Dist: torch>=2.0.0
Requires-Dist: tqdm>=4.65.0
Requires-Dist: transformers>=4.40.0
Provides-Extra: all
Requires-Dist: accelerate>=0.26.0; extra == 'all'
Requires-Dist: fastapi>=0.109.0; extra == 'all'
Requires-Dist: open-clip-torch>=2.24.0; extra == 'all'
Requires-Dist: pytest>=8.0.0; extra == 'all'
Requires-Dist: ruff>=0.1.0; extra == 'all'
Requires-Dist: uvicorn>=0.27.0; extra == 'all'
Provides-Extra: clip
Requires-Dist: open-clip-torch>=2.24.0; extra == 'clip'
Provides-Extra: dev
Requires-Dist: pytest>=8.0.0; extra == 'dev'
Requires-Dist: ruff>=0.1.0; extra == 'dev'
Provides-Extra: gpu
Requires-Dist: accelerate>=0.26.0; extra == 'gpu'
Provides-Extra: serve
Requires-Dist: fastapi>=0.109.0; extra == 'serve'
Requires-Dist: uvicorn>=0.27.0; extra == 'serve'
